signalAI/__init__.py
signalAI/experiments/__init__.py
signalAI/experiments/base.py
signalAI/experiments/features_1d.py
signalAI/experiments/torch_data.py
signalAI/utils/__init__.py
signalAI/utils/experiment_result.py
signalAI/utils/fold_idx_generator.py
signalAI/utils/group_dataset.py
signalAI/utils/metrics.py
signalAI-0.0.6.dist-info/METADATA
signalAI-0.0.6.dist-info/WHEEL
signalAI-0.0.6.dist-info/top_level.txt
signalAI-0.0.6.dist-info/RECORD
