Metadata-Version: 2.1
Name: signalAI
Version: 0.0.6
Summary: A package for vibration signal analysis using AI
Home-page: https://github.com/VitorBonella/SignAI-Framework
Author: Vitor Bonella
License: UNKNOWN
Platform: UNKNOWN
Requires-Dist: matplotlib
Requires-Dist: numpy
Requires-Dist: pandas
Requires-Dist: scikit-learn
Requires-Dist: seaborn
Requires-Dist: torch
Requires-Dist: tqdm
